README.md
setup.cfg
setup.py
athec/__init__.py
athec/color.py
athec/misc.py
athec.egg-info/PKG-INFO
athec.egg-info/SOURCES.txt
athec.egg-info/dependency_links.txt
athec.egg-info/requires.txt
athec.egg-info/top_level.txt